futureasync/__init__.py
futureasync/futureasync.py
pymaniac/__init__.py
pymaniac/main.py
pymaniac/pymaniac.py
futureasync-2.0.dist-info/LICENSE
futureasync-2.0.dist-info/METADATA
futureasync-2.0.dist-info/WHEEL
futureasync-2.0.dist-info/top_level.txt
futureasync-2.0.dist-info/RECORD
