Metadata-Version: 2.1
Name: futureasync
Version: 2.0
Summary: Simple python module to perform your web requests simultaneously in an asynchronous and colors toolkit, simple, efficient and powerful way.
Home-page: https://github.com/votre_compte/futureasync
Author: futureasync
Author-email: pymaniaclib@hotmail.com
License: MIT
Classifier: Programming Language :: Python :: 3
Classifier: License :: OSI Approved :: MIT License
Classifier: Operating System :: OS Independent
License-File: LICENSE
Requires-Dist: colorama
Requires-Dist: httpx
Requires-Dist: pyautogui
Requires-Dist: pycountry
Requires-Dist: requests
Requires-Dist: telegram
